elemai/__init__.py
elemai/chat.py
elemai/client.py
elemai/config.py
elemai/sentinel.py
elemai/task.py
elemai/template.py
elemai-0.4.0.dist-info/licenses/LICENSE
elemai-0.4.0.dist-info/METADATA
elemai-0.4.0.dist-info/WHEEL
elemai-0.4.0.dist-info/top_level.txt
elemai-0.4.0.dist-info/RECORD
