Metadata-Version: 2.4
Name: elemai
Version: 0.4.0
Summary: An AI LLM coding library
Author-email: Maxime Rivest <mrive052@gmail.com>
License: MIT
Project-URL: Homepage, https://github.com/maximerivest/elemai
Project-URL: Documentation, https://github.com/maximerivest/elemai
Project-URL: Repository, https://github.com/maximerivest/elemai
Classifier: Development Status :: 3 - Alpha
Classifier: Intended Audience :: Developers
Classifier: License :: OSI Approved :: MIT License
Classifier: Programming Language :: Python :: 3
Classifier: Programming Language :: Python :: 3.8
Classifier: Programming Language :: Python :: 3.9
Classifier: Programming Language :: Python :: 3.10
Classifier: Programming Language :: Python :: 3.11
Classifier: Programming Language :: Python :: 3.12
Requires-Python: >=3.8
License-File: LICENSE
Requires-Dist: litellm>=1.0.0
Requires-Dist: pydantic>=2.0.0
Requires-Dist: pyyaml>=6.0
Provides-Extra: dev
Requires-Dist: pytest>=7.0; extra == "dev"
Requires-Dist: pytest-cov>=4.0; extra == "dev"
Requires-Dist: black>=23.0; extra == "dev"
Requires-Dist: isort>=5.0; extra == "dev"
Requires-Dist: mypy>=1.0; extra == "dev"
Requires-Dist: ruff>=0.1.0; extra == "dev"
Dynamic: license-file
